UART/TRANSMITTER/transmitter.v
module baud_generator(input clk,reset,
input [1:0]baud_sel,
output reg intx,
output reg inrx);
//frequency=150 mhz
reg [31:0]baud_partition_tx = 0;
reg [31:0]baud_partition_rx = 0;
reg [31:0]count_tx=0;
reg [31:0]count_rx=0;


always @(*) begin
 case (baud_sel)
	 2'b00:begin
	  baud_partition_tx=31250;
	  baud_partition_rx=31250;end
          
	  2'b01:begin
		  baud_partition_tx=7813;
		  baud_partition_rx=7813; end

		  2'b10:begin
			  baud_partition_tx=325;
			  baud_partition_rx=325; end

			  2'b11:begin 
 			  baud_partition_tx=162;
			  baud_partition_rx=162;end

endcase
end


always @ (posedge clk or posedge reset) begin

if (reset) begin
 intx<=0;
 count_tx<=0;
end
else if (count_tx == baud_partition_tx) begin
	intx<=1'b1;
	count_tx<=0;
	end
	else begin
		intx<=0;
		count_tx<=count_tx+1'b1;
		end end

always @ (posedge clk or posedge reset) begin

if (reset) begin
        inrx<=0;
       	count_rx<=0;
end
else if(count_rx == baud_partition_tx) begin
                inrx<=1'b1;
	 	count_rx <=0;

	end
	else begin
		inrx<=0;
		count_rx<=count_rx+1'b1;end
	end

	endmodule



module transmitter (
input clk,
input reset,
input [7:0]data_in,
input intx,
output reg [10:0]out_tx);


reg [3:0]count;
reg [1:0]parity_sel;
reg parity;
reg [1:0]next_state,state;
reg [7:0]data_reg;
parameter idle=3'd1;
parameter tx_start=3'd2;
parameter tx_parity=3'd3;
parameter tx_stop=3'd4;

always @ (posedge clk or posedge reset) begin
 if (reset) begin
    state<=idle;
    //out_tx<=11'b11111111111;
    count<=0;
end
else if(intx) begin
      state<=next_state;    
end
end

always @ (*) begin

case(state)

 idle: begin 
     out_tx<=0;
     data_reg <= data_in;
     count<=0;
     next_state<= tx_start;
end


 tx_start: begin
	 out_tx<={out_tx[9:0],data_reg[0]};
	 count<=count+1;
	 data_reg<=data_reg>>1;
	 if(count==7) 
		 next_state<=tx_parity;

 end

 tx_parity:begin 
     case(parity_sel)
	     2'b00:parity=1'b0;
	     2'b10:parity=~(^data_in);
	     2'b01:parity=~data_in;
	    default : parity=1'b0; 
    endcase
	    out_tx <= {out_tx[9:0],parity};
	    next_state<=tx_stop;

end 

tx_stop:begin
	out_tx<={out_tx[9:0],1'b1};
	next_state<=idle;
end
endcase
end
endmodule

UART/TRANSMITTER/transmitter_tb.v
module transmitter_tb;
 reg clk;
 reg reset;
 reg [7:0]data_in;
 wire intx;
 wire [10:0]out_tx;

 reg [1:0]baud_sel;
 baud_generator bg (
        .clk(clk),
        .reset(reset),
        .baud_sel(baud_sel),
        .intx(intx),
        .inrx()
    );
 transmitter uut (
        .clk(clk),
        .reset(reset),
        .data_in(data_in),
        .intx(intx),
        .out_tx(out_tx)
    );
    
    initial begin
   clk=0;
   forever #5 clk=~clk;
end
initial begin
	$dumpfile("transmitter.vcd");
	$dumpvars(); end

initial begin
$display("Time\tclk\trset\tdata\tintx\tout_tx");
$monitor("%0t\t%b\t%b\t%b\t%b\t%b",$time,clk,reset,data_in,intx,out_tx);

reset = 1; baud_sel = 2'b10; // 460800 baud
        #20 reset = 0;

        data_in = 8'b10101010; 
	#200000 $finish;
end 
endmodule

UART/TRANSMITTER/transmitter.vcd
$date
	Fri Jun 20 16:07:41 2025
$end
$version
	Icarus Verilog
$end
$timescale
	1s
$end
$scope module transmitter_tb $end
$var wire 11 ! out_tx [10:0] $end
$var wire 1 " intx $end
$var reg 2 # baud_sel [1:0] $end
$var reg 1 $ clk $end
$var reg 8 % data_in [7:0] $end
$var reg 1 & reset $end
$scope module bg $end
$var wire 2 ' baud_sel [1:0] $end
$var wire 1 $ clk $end
$var wire 1 & reset $end
$var reg 32 ( baud_partition_rx [31:0] $end
$var reg 32 ) baud_partition_tx [31:0] $end
$var reg 32 * count_rx [31:0] $end
$var reg 32 + count_tx [31:0] $end
$var reg 1 , inrx $end
$var reg 1 " intx $end
$upscope $end
$scope module uut $end
$var wire 1 $ clk $end
$var wire 8 - data_in [7:0] $end
$var wire 1 " intx $end
$var wire 1 & reset $end
$var parameter 3 . idle $end
$var parameter 3 / tx_parity $end
$var parameter 3 0 tx_start $end
$var parameter 3 1 tx_stop $end
$var reg 4 2 count [3:0] $end
$var reg 8 3 data_reg [7:0] $end
$var reg 2 4 next_state [1:0] $end
$var reg 11 5 out_tx [10:0] $end
$var reg 1 6 parity $end
$var reg 2 7 parity_sel [1:0] $end
$var reg 2 8 state [1:0] $end
$upscope $end
$upscope $end
$enddefinitions $end
$comment Show the parameter values. $end
$dumpall
b100 1
b10 0
b11 /
b1 .
$end
#0
$dumpvars
b1 8
bx 7
x6
b0 5
b10 4
bx 3
b0 2
bx -
0,
b0 +
b0 *
b101000101 )
b101000101 (
b10 '
1&
bx %
0$
b10 #
0"
b0 !
$end
#5
b0 !
b0 5
1$
#10
0$
#15
b0 !
b0 5
1$
#20
b10101010 3
0$
b10101010 %
b10101010 -
0&
#25
b1 *
b1 +
1$
#30
0$
#35
b10 +
b10 *
1$
#40
0$
#45
b11 *
b11 +
1$
#50
0$
#55
b100 +
b100 *
1$
#60
0$
#65
b101 *
b101 +
1$
#70
0$
#75
b110 +
b110 *
1$
#80
0$
#85
b111 *
b111 +
1$
#90
0$
#95
b1000 +
b1000 *
1$
#100
0$
#105
b1001 *
b1001 +
1$
#110
0$
#115
b1010 +
b1010 *
1$
#120
0$
#125
b1011 *
b1011 +
1$
#130
0$
#135
b1100 +
b1100 *
1$
#140
0$
#145
b1101 *
b1101 +
1$
#150
0$
#155
b1110 +
b1110 *
1$
#160
0$
#165
b1111 *
b1111 +
1$
#170
0$
#175
b10000 +
b10000 *
1$
#180
0$
#185
b10001 *
b10001 +
1$
#190
0$
#195
b10010 +
b10010 *
1$
#200
0$
#205
b10011 *
b10011 +
1$
#210
0$
#215
b10100 +
b10100 *
1$
#220
0$
#225
b10101 *
b10101 +
1$
#230
0$
#235
b10110 +
b10110 *
1$
#240
0$
#245
b10111 *
b10111 +
1$
#250
0$
#255
b11000 +
b11000 *
1$
#260
0$
#265
b11001 *
b11001 +
1$
#270
0$
#275
b11010 +
b11010 *
1$
#280
0$
#285
b11011 *
b11011 +
1$
#290
0$
#295
b11100 +
b11100 *
1$
#300
0$
#305
b11101 *
b11101 +
1$
#310
0$
#315
b11110 +
b11110 *
1$
#320
0$
#325
b11111 *
b11111 +
1$
#330
0$
#335
b100000 +
b100000 *
1$
#340
0$
#345
b100001 *
b100001 +
1$
#350
0$
#355
b100010 +
b100010 *
1$
#360
0$
#365
b100011 *
b100011 +
1$
#370
0$
#375
b100100 +
b100100 *
1$
#380
0$
#385
b100101 *
b100101 +
1$
#390
0$
#395
b100110 +
b100110 *
1$
#400
0$
#405
b100111 *
b100111 +
1$
#410
0$
#415
b101000 +
b101000 *
1$
#420
0$
#425
b101001 *
b101001 +
1$
#430
0$
#435
b101010 +
b101010 *
1$
#440
0$
#445
b101011 *
b101011 +
1$
#450
0$
#455
b101100 +
b101100 *
1$
#460
0$
#465
b101101 *
b101101 +
1$
#470
0$
#475
b101110 +
b101110 *
1$
#480
0$
#485
b101111 *
b101111 +
1$
#490
0$
#495
b110000 +
b110000 *
1$
#500
0$
#505
b110001 *
b110001 +
1$
#510
0$
#515
b110010 +
b110010 *
1$
#520
0$
#525
b110011 *
b110011 +
1$
#530
0$
#535
b110100 +
b110100 *
1$
#540
0$
#545
b110101 *
b110101 +
1$
#550
0$
#555
b110110 +
b110110 *
1$
#560
0$
#565
b110111 *
b110111 +
1$
#570
0$
#575
b111000 +
b111000 *
1$
#580
0$
#585
b111001 *
b111001 +
1$
#590
0$
#595
b111010 +
b111010 *
1$
#600
0$
#605
b111011 *
b111011 +
1$
#610
0$
#615
b111100 +
b111100 *
1$
#620
0$
#625
b111101 *
b111101 +
1$
#630
0$
#635
b111110 +
b111110 *
1$
#640
0$
#645
b111111 *
b111111 +
1$
#650
0$
#655
b1000000 +
b1000000 *
1$
#660
0$
#665
b1000001 *
b1000001 +
1$
#670
0$
#675
b1000010 +
b1000010 *
1$
#680
0$
#685
b1000011 *
b1000011 +
1$
#690
0$
#695
b1000100 +
b1000100 *
1$
#700
0$
#705
b1000101 *
b1000101 +
1$
#710
0$
#715
b1000110 +
b1000110 *
1$
#720
0$
#725
b1000111 *
b1000111 +
1$
#730
0$
#735
b1001000 +
b1001000 *
1$
#740
0$
#745
b1001001 *
b1001001 +
1$
#750
0$
#755
b1001010 +
b1001010 *
1$
#760
0$
#765
b1001011 *
b1001011 +
1$
#770
0$
#775
b1001100 +
b1001100 *
1$
#780
0$
#785
b1001101 *
b1001101 +
1$
#790
0$
#795
b1001110 +
b1001110 *
1$
#800
0$
#805
b1001111 *
b1001111 +
1$
#810
0$
#815
b1010000 +
b1010000 *
1$
#820
0$
#825
b1010001 *
b1010001 +
1$
#830
0$
#835
b1010010 +
b1010010 *
1$
#840
0$
#845
b1010011 *
b1010011 +
1$
#850
0$
#855
b1010100 +
b1010100 *
1$
#860
0$
#865
b1010101 *
b1010101 +
1$
#870
0$
#875
b1010110 +
b1010110 *
1$
#880
0$
#885
b1010111 *
b1010111 +
1$
#890
0$
#895
b1011000 +
b1011000 *
1$
#900
0$
#905
b1011001 *
b1011001 +
1$
#910
0$
#915
b1011010 +
b1011010 *
1$
#920
0$
#925
b1011011 *
b1011011 +
1$
#930
0$
#935
b1011100 +
b1011100 *
1$
#940
0$
#945
b1011101 *
b1011101 +
1$
#950
0$
#955
b1011110 +
b1011110 *
1$
#960
0$
#965
b1011111 *
b1011111 +
1$
#970
0$
#975
b1100000 +
b1100000 *
1$
#980
0$
#985
b1100001 *
b1100001 +
1$
#990
0$
#995
b1100010 +
b1100010 *
1$
#1000
0$
#1005
b1100011 *
b1100011 +
1$
#1010
0$
#1015
b1100100 +
b1100100 *
1$
#1020
0$
#1025
b1100101 *
b1100101 +
1$
#1030
0$
#1035
b1100110 +
b1100110 *
1$
#1040
0$
#1045
b1100111 *
b1100111 +
1$
#1050
0$
#1055
b1101000 +
b1101000 *
1$
#1060
0$
#1065
b1101001 *
b1101001 +
1$
#1070
0$
#1075
b1101010 +
b1101010 *
1$
#1080
0$
#1085
b1101011 *
b1101011 +
1$
#1090
0$
#1095
b1101100 +
b1101100 *
1$
#1100
0$
#1105
b1101101 *
b1101101 +
1$
#1110
0$
#1115
b1101110 +
b1101110 *
1$
#1120
0$
#1125
b1101111 *
b1101111 +
1$
#1130
0$
#1135
b1110000 +
b1110000 *
1$
#1140
0$
#1145
b1110001 *
b1110001 +
1$
#1150
0$
#1155
b1110010 +
b1110010 *
1$
#1160
0$
#1165
b1110011 *
b1110011 +
1$
#1170
0$
#1175
b1110100 +
b1110100 *
1$
#1180
0$
#1185
b1110101 *
b1110101 +
1$
#1190
0$
#1195
b1110110 +
b1110110 *
1$
#1200
0$
#1205
b1110111 *
b1110111 +
1$
#1210
0$
#1215
b1111000 +
b1111000 *
1$
#1220
0$
#1225
b1111001 *
b1111001 +
1$
#1230
0$
#1235
b1111010 +
b1111010 *
1$
#1240
0$
#1245
b1111011 *
b1111011 +
1$
#1250
0$
#1255
b1111100 +
b1111100 *
1$
#1260
0$
#1265
b1111101 *
b1111101 +
1$
#1270
0$
#1275
b1111110 +
b1111110 *
1$
#1280
0$
#1285
b1111111 *
b1111111 +
1$
#1290
0$
#1295
b10000000 +
b10000000 *
1$
#1300
0$
#1305
b10000001 *
b10000001 +
1$
#1310
0$
#1315
b10000010 +
b10000010 *
1$
#1320
0$
#1325
b10000011 *
b10000011 +
1$
#1330
0$
#1335
b10000100 +
b10000100 *
1$
#1340
0$
#1345
b10000101 *
b10000101 +
1$
#1350
0$
#1355
b10000110 +
b10000110 *
1$
#1360
0$
#1365
b10000111 *
b10000111 +
1$
#1370
0$
#1375
b10001000 +
b10001000 *
1$
#1380
0$
#1385
b10001001 *
b10001001 +
1$
#1390
0$
#1395
b10001010 +
b10001010 *
1$
#1400
0$
#1405
b10001011 *
b10001011 +
1$
#1410
0$
#1415
b10001100 +
b10001100 *
1$
#1420
0$
#1425
b10001101 *
b10001101 +
1$
#1430
0$
#1435
b10001110 +
b10001110 *
1$
#1440
0$
#1445
b10001111 *
b10001111 +
1$
#1450
0$
#1455
b10010000 +
b10010000 *
1$
#1460
0$
#1465
b10010001 *
b10010001 +
1$
#1470
0$
#1475
b10010010 +
b10010010 *
1$
#1480
0$
#1485
b10010011 *
b10010011 +
1$
#1490
0$
#1495
b10010100 +
b10010100 *
1$
#1500
0$
#1505
b10010101 *
b10010101 +
1$
#1510
0$
#1515
b10010110 +
b10010110 *
1$
#1520
0$
#1525
b10010111 *
b10010111 +
1$
#1530
0$
#1535
b10011000 +
b10011000 *
1$
#1540
0$
#1545
b10011001 *
b10011001 +
1$
#1550
0$
#1555
b10011010 +
b10011010 *
1$
#1560
0$
#1565
b10011011 *
b10011011 +
1$
#1570
0$
#1575
b10011100 +
b10011100 *
1$
#1580
0$
#1585
b10011101 *
b10011101 +
1$
#1590
0$
#1595
b10011110 +
b10011110 *
1$
#1600
0$
#1605
b10011111 *
b10011111 +
1$
#1610
0$
#1615
b10100000 +
b10100000 *
1$
#1620
0$
#1625
b10100001 *
b10100001 +
1$
#1630
0$
#1635
b10100010 +
b10100010 *
1$
#1640
0$
#1645
b10100011 *
b10100011 +
1$
#1650
0$
#1655
b10100100 +
b10100100 *
1$
#1660
0$
#1665
b10100101 *
b10100101 +
1$
#1670
0$
#1675
b10100110 +
b10100110 *
1$
#1680
0$
#1685
b10100111 *
b10100111 +
1$
#1690
0$
#1695
b10101000 +
b10101000 *
1$
#1700
0$
#1705
b10101001 *
b10101001 +
1$
#1710
0$
#1715
b10101010 +
b10101010 *
1$
#1720
0$
#1725
b10101011 *
b10101011 +
1$
#1730
0$
#1735
b10101100 +
b10101100 *
1$
#1740
0$
#1745
b10101101 *
b10101101 +
1$
#1750
0$
#1755
b10101110 +
b10101110 *
1$
#1760
0$
#1765
b10101111 *
b10101111 +
1$
#1770
0$
#1775
b10110000 +
b10110000 *
1$
#1780
0$
#1785
b10110001 *
b10110001 +
1$
#1790
0$
#1795
b10110010 +
b10110010 *
1$
#1800
0$
#1805
b10110011 *
b10110011 +
1$
#1810
0$
#1815
b10110100 +
b10110100 *
1$
#1820
0$
#1825
b10110101 *
b10110101 +
1$
#1830
0$
#1835
b10110110 +
b10110110 *
1$
#1840
0$
#1845
b10110111 *
b10110111 +
1$
#1850
0$
#1855
b10111000 +
b10111000 *
1$
#1860
0$
#1865
b10111001 *
b10111001 +
1$
#1870
0$
#1875
b10111010 +
b10111010 *
1$
#1880
0$
#1885
b10111011 *
b10111011 +
1$
#1890
0$
#1895
b10111100 +
b10111100 *
1$
#1900
0$
#1905
b10111101 *
b10111101 +
1$
#1910
0$
#1915
b10111110 +
b10111110 *
1$
#1920
0$
#1925
b10111111 *
b10111111 +
1$
#1930
0$
#1935
b11000000 +
b11000000 *
1$
#1940
0$
#1945
b11000001 *
b11000001 +
1$
#1950
0$
#1955
b11000010 +
b11000010 *
1$
#1960
0$
#1965
b11000011 *
b11000011 +
1$
#1970
0$
#1975
b11000100 +
b11000100 *
1$
#1980
0$
#1985
b11000101 *
b11000101 +
1$
#1990
0$
#1995
b11000110 +
b11000110 *
1$
#2000
0$
#2005
b11000111 *
b11000111 +
1$
#2010
0$
#2015
b11001000 +
b11001000 *
1$
#2020
0$
#2025
b11001001 *
b11001001 +
1$
#2030
0$
#2035
b11001010 +
b11001010 *
1$
#2040
0$
#2045
b11001011 *
b11001011 +
1$
#2050
0$
#2055
b11001100 +
b11001100 *
1$
#2060
0$
#2065
b11001101 *
b11001101 +
1$
#2070
0$
#2075
b11001110 +
b11001110 *
1$
#2080
0$
#2085
b11001111 *
b11001111 +
1$
#2090
0$
#2095
b11010000 +
b11010000 *
1$
#2100
0$
#2105
b11010001 *
b11010001 +
1$
#2110
0$
#2115
b11010010 +
b11010010 *
1$
#2120
0$
#2125
b11010011 *
b11010011 +
1$
#2130
0$
#2135
b11010100 +
b11010100 *
1$
#2140
0$
#2145
b11010101 *
b11010101 +
1$
#2150
0$
#2155
b11010110 +
b11010110 *
1$
#2160
0$
#2165
b11010111 *
b11010111 +
1$
#2170
0$
#2175
b11011000 +
b11011000 *
1$
#2180
0$
#2185
b11011001 *
b11011001 +
1$
#2190
0$
#2195
b11011010 +
b11011010 *
1$
#2200
0$
#2205
b11011011 *
b11011011 +
1$
#2210
0$
#2215
b11011100 +
b11011100 *
1$
#2220
0$
#2225
b11011101 *
b11011101 +
1$
#2230
0$
#2235
b11011110 +
b11011110 *
1$
#2240
0$
#2245
b11011111 *
b11011111 +
1$
#2250
0$
#2255
b11100000 +
b11100000 *
1$
#2260
0$
#2265
b11100001 *
b11100001 +
1$
#2270
0$
#2275
b11100010 +
b11100010 *
1$
#2280
0$
#2285
b11100011 *
b11100011 +
1$
#2290
0$
#2295
b11100100 +
b11100100 *
1$
#2300
0$
#2305
b11100101 *
b11100101 +
1$
#2310
0$
#2315
b11100110 +
b11100110 *
1$
#2320
0$
#2325
b11100111 *
b11100111 +
1$
#2330
0$
#2335
b11101000 +
b11101000 *
1$
#2340
0$
#2345
b11101001 *
b11101001 +
1$
#2350
0$
#2355
b11101010 +
b11101010 *
1$
#2360
0$
#2365
b11101011 *
b11101011 +
1$
#2370
0$
#2375
b11101100 +
b11101100 *
1$
#2380
0$
#2385
b11101101 *
b11101101 +
1$
#2390
0$
#2395
b11101110 +
b11101110 *
1$
#2400
0$
#2405
b11101111 *
b11101111 +
1$
#2410
0$
#2415
b11110000 +
b11110000 *
1$
#2420
0$
#2425
b11110001 *
b11110001 +
1$
#2430
0$
#2435
b11110010 +
b11110010 *
1$
#2440
0$
#2445
b11110011 *
b11110011 +
1$
#2450
0$
#2455
b11110100 +
b11110100 *
1$
#2460
0$
#2465
b11110101 *
b11110101 +
1$
#2470
0$
#2475
b11110110 +
b11110110 *
1$
#2480
0$
#2485
b11110111 *
b11110111 +
1$
#2490
0$
#2495
b11111000 +
b11111000 *
1$
#2500
0$
#2505
b11111001 *
b11111001 +
1$
#2510
0$
#2515
b11111010 +
b11111010 *
1$
#2520
0$
#2525
b11111011 *
b11111011 +
1$
#2530
0$
#2535
b11111100 +
b11111100 *
1$
#2540
0$
#2545
b11111101 *
b11111101 +
1$
#2550
0$
#2555
b11111110 +
b11111110 *
1$
#2560
0$
#2565
b11111111 *
b11111111 +
1$
#2570
0$
#2575
b100000000 +
b100000000 *
1$
#2580
0$
#2585
b100000001 *
b100000001 +
1$
#2590
0$
#2595
b100000010 +
b100000010 *
1$
#2600
0$
#2605
b100000011 *
b100000011 +
1$
#2610
0$
#2615
b100000100 +
b100000100 *
1$
#2620
0$
#2625
b100000101 *
b100000101 +
1$
#2630
0$
#2635
b100000110 +
b100000110 *
1$
#2640
0$
#2645
b100000111 *
b100000111 +
1$
#2650
0$
#2655
b100001000 +
b100001000 *
1$
#2660
0$
#2665
b100001001 *
b100001001 +
1$
#2670
0$
#2675
b100001010 +
b100001010 *
1$
#2680
0$
#2685
b100001011 *
b100001011 +
1$
#2690
0$
#2695
b100001100 +
b100001100 *
1$
#2700
0$
#2705
b100001101 *
b100001101 +
1$
#2710
0$
#2715
b100001110 +
b100001110 *
1$
#2720
0$
#2725
b100001111 *
b100001111 +
1$
#2730
0$
#2735
b100010000 +
b100010000 *
1$
#2740
0$
#2745
b100010001 *
b100010001 +
1$
#2750
0$
#2755
b100010010 +
b100010010 *
1$
#2760
0$
#2765
b100010011 *
b100010011 +
1$
#2770
0$
#2775
b100010100 +
b100010100 *
1$
#2780
0$
#2785
b100010101 *
b100010101 +
1$
#2790
0$
#2795
b100010110 +
b100010110 *
1$
#2800
0$
#2805
b100010111 *
b100010111 +
1$
#2810
0$
#2815
b100011000 +
b100011000 *
1$
#2820
0$
#2825
b100011001 *
b100011001 +
1$
#2830
0$
#2835
b100011010 +
b100011010 *
1$
#2840
0$
#2845
b100011011 *
b100011011 +
1$
#2850
0$
#2855
b100011100 +
b100011100 *
1$
#2860
0$
#2865
b100011101 *
b100011101 +
1$
#2870
0$
#2875
b100011110 +
b100011110 *
1$
#2880
0$
#2885
b100011111 *
b100011111 +
1$
#2890
0$
#2895
b100100000 +
b100100000 *
1$
#2900
0$
#2905
b100100001 *
b100100001 +
1$
#2910
0$
#2915
b100100010 +
b100100010 *
1$
#2920
0$
#2925
b100100011 *
b100100011 +
1$
#2930
0$
#2935
b100100100 +
b100100100 *
1$
#2940
0$
#2945
b100100101 *
b100100101 +
1$
#2950
0$
#2955
b100100110 +
b100100110 *
1$
#2960
0$
#2965
b100100111 *
b100100111 +
1$
#2970
0$
#2975
b100101000 +
b100101000 *
1$
#2980
0$
#2985
b100101001 *
b100101001 +
1$
#2990
0$
#2995
b100101010 +
b100101010 *
1$
#3000
0$
#3005
b100101011 *
b100101011 +
1$
#3010
0$
#3015
b100101100 +
b100101100 *
1$
#3020
0$
#3025
b100101101 *
b100101101 +
1$
#3030
0$
#3035
b100101110 +
b100101110 *
1$
#3040
0$
#3045
b100101111 *
b100101111 +
1$
#3050
0$
#3055
b100110000 +
b100110000 *
1$
#3060
0$
#3065
b100110001 *
b100110001 +
1$
#3070
0$
#3075
b100110010 +
b100110010 *
1$
#3080
0$
#3085
b100110011 *
b100110011 +
1$
#3090
0$
#3095
b100110100 +
b100110100 *
1$
#3100
0$
#3105
b100110101 *
b100110101 +
1$
#3110
0$
#3115
b100110110 +
b100110110 *
1$
#3120
0$
#3125
b100110111 *
b100110111 +
1$
#3130
0$
#3135
b100111000 +
b100111000 *
1$
#3140
0$
#3145
b100111001 *
b100111001 +
1$
#3150
0$
#3155
b100111010 +
b100111010 *
1$
#3160
0$
#3165
b100111011 *
b100111011 +
1$
#3170
0$
#3175
b100111100 +
b100111100 *
1$
#3180
0$
#3185
b100111101 *
b100111101 +
1$
#3190
0$
#3195
b100111110 +
b100111110 *
1$
#3200
0$
#3205
b100111111 *
b100111111 +
1$
#3210
0$
#3215
b101000000 +
b101000000 *
1$
#3220
0$
#3225
b101000001 *
b101000001 +
1$
#3230
0$
#3235
b101000010 +
b101000010 *
1$
#3240
0$
#3245
b101000011 *
b101000011 +
1$
#3250
0$
#3255
b101000100 +
b101000100 *
1$
#3260
0$
#3265
b101000101 *
b101000101 +
1$
#3270
0$
#3275
b0 +
1"
b0 *
1,
1$
